finance_news_scraper/__init__.py
finance_news_scraper/__main__.py
finance_news_scraper/mongo_client.py
finance_news_scraper/news_sources.py
finance_news_scraper/sentiment.py
finance_news_scraper-0.0.4.dist-info/LICENSE
finance_news_scraper-0.0.4.dist-info/METADATA
finance_news_scraper-0.0.4.dist-info/WHEEL
finance_news_scraper-0.0.4.dist-info/top_level.txt
finance_news_scraper-0.0.4.dist-info/RECORD
