Metadata-Version: 2.1
Name: finance-news-scraper
Version: 0.0.4
Summary: Collect, store and access finance news locally
Author: Lukas Kreussel
License: MIT License        
Project-URL: Homepage, https://github.com/LLukas22/Finance-Data-Scraper
Project-URL: Bug Tracker, https://github.com/LLukas22/Finance-Data-Scraper/issues
Classifier: Programming Language :: Python :: 3
Classifier: License :: OSI Approved :: MIT License
Classifier: Operating System :: OS Independent
Requires-Python: >=3.10
License-File: LICENSE
Requires-Dist: pytz (>=2022.1)
Requires-Dist: pandas (>=1.4.2)
Requires-Dist: numpy (>=1.22.3)
Requires-Dist: requests (>=2.28.1)
Requires-Dist: tqdm (>=4.64.0)
Requires-Dist: pymongo (>=4.2.0)
Requires-Dist: transformers[torch] (>=4.19.4)
Requires-Dist: beautifulsoup4 (>=4.11.1)
Requires-Dist: newspaper3k (>=0.2.8)
Requires-Dist: dateparser (>=1.1.1)
Requires-Dist: cchardet (>=2.1.7)
Requires-Dist: google-news-feed (>=1.0.0)
